adversarial_attacks_white_black_box/__init__.py
adversarial_attacks_white_black_box/adversarial_attack_base.py
adversarial_attacks_white_black_box/adversarial_attacks.py
adversarial_attacks_white_black_box/helper_functions.py
adversarial_attacks_white_black_box/main.py
adversarial_attacks_white_black_box/run.py
adversarial_attacks_white_black_box-0.1.7.dist-info/LICENSE.md
adversarial_attacks_white_black_box-0.1.7.dist-info/METADATA
adversarial_attacks_white_black_box-0.1.7.dist-info/WHEEL
adversarial_attacks_white_black_box-0.1.7.dist-info/entry_points.txt
adversarial_attacks_white_black_box-0.1.7.dist-info/top_level.txt
adversarial_attacks_white_black_box-0.1.7.dist-info/RECORD
