Metadata-Version: 2.1
Name: adversarial-attacks-white-black-box
Version: 0.1.7
Summary: Perform White-Box and Black-Box adversarial attacks on images.
Home-page: https://github.com/sifubro/Adversarial_Attacks
Author: Theodoros Kasioumis
Author-email: theodoros.kasioumis@gmail.com
License: UNKNOWN
Platform: UNKNOWN
Classifier: Programming Language :: Python :: 3
Classifier: License :: OSI Approved :: MIT License
Classifier: Operating System :: OS Independent
Requires-Python: >=3.6
License-File: LICENSE.md
Requires-Dist: numpy (==1.23.5)
Requires-Dist: requests (==2.27.1)
Requires-Dist: pillow (==9.3.0)
Requires-Dist: tensorflow (==2.13.0)
Requires-Dist: onnxruntime (==1.13.1)
Requires-Dist: rembg (==2.0.57)
